<?xml version="1.0" encoding="UTF-8"?>
<courses>
    <course academic_year="2015" course_id="110225" class_number="16220" school_id="fas" section="001" term_code="spring">
        <catalog_info>
            <title short_title="GOV 2011">Graduate Practicum in Survey Research</title>
            <description>This course is geared to graduate students who are designing an original survey. Assignments cover core aspects of survey design. By the end of the course, students should have produced a comprehensive research plan which can be implemented or submitted as part of a proposal to a funding agency.</description>
            <department code="GOVM">Government</department>
            <course_group code="GOV">Government</course_group>
            <course_type>Seminar</course_type>
            <credits>4</credits>
            <meeting_schedule>
                <meeting days_of_week="Wednesday" end_time="17:59:00" location="" start_time="16:00:00"/>
            </meeting_schedule>
        </catalog_info>
        <staff>
            <person id="d1e65808a1310" role="1" seniority_sort="1">
                <display_name>Chase Harrison</display_name>
            </person>
        </staff>
    </course>
</courses>