<?xml version="1.0" encoding="UTF-8"?>
<courses>
    <course academic_year="2015" course_id="110416" class_number="11055" school_id="fas" section="001" term_code="spring">
        <catalog_info>
            <title short_title="CELLBIO 359">Intracellular Signaling Pathways in the Regulation of Cell Growth and Differentiation</title>
            <department code="MDSC">Medical Sciences</department>
            <course_group code="CELLBIO">Cell Biology</course_group>
            <course_type>Reading and Research</course_type>
            <credits>4</credits>
        </catalog_info>
        <staff>
            <person id="d1e142340a1310" role="1" seniority_sort="1">
                <display_name>David Frank</display_name>
            </person>
        </staff>
    </course>
</courses>