<?xml version="1.0" encoding="UTF-8"?>
<courses>
    <course academic_year="2015" course_id="111169" class_number="10176" school_id="fas" section="001" term_code="fall">
        <catalog_info>
            <title short_title="PHYSICS 341A">Topics in Experimental Atomic and Condensed Matter Physics</title>
            <department code="PHYS">Physics</department>
            <course_group code="PHYSICS">Physics</course_group>
            <course_type>Reading Course</course_type>
            <credits>4</credits>
        </catalog_info>
        <staff>
            <person id="d1e71095a1310" role="1" seniority_sort="1">
                <display_name>Markus Greiner</display_name>
            </person>
        </staff>
    </course>
</courses>