<?xml version="1.0" encoding="UTF-8"?>
<courses>
    <course academic_year="2015" course_id="117879" class_number="12404" school_id="fas" section="001" term_code="spring">
        <catalog_info>
            <title short_title="PSY 1952">Multivariate Analysis in Psychology</title>
            <notes>Lecture: M., W., 12-1:30; Lab: Th., 6:30 - 8   </notes>
            <prereq>Recommended: Psychology 1900.</prereq>
            <description>This course introduces the empirical measurement of abstract constructs and multivariate analysis. Topics include: reliability and validity, multiple regression, exploratory and confirmatory factor analyses, discriminant function analysis and structural equation modeling.</description>
            <department code="PSYC">Psychology</department>
            <course_group code="PSY">Psychology</course_group>
            <course_type>Lecture</course_type>
            <credits>4</credits>
            <meeting_schedule>
                <meeting days_of_week="Monday Wednesday" end_time="13:29:00" location="" start_time="12:00:00"/>
            </meeting_schedule>
        </catalog_info>
        <staff>
            <person id="d1e73727a1310" role="1" seniority_sort="1">
                <display_name>James Sidanius</display_name>
            </person>
        </staff>
    </course>
</courses>