<?xml version="1.0" encoding="UTF-8"?>
<courses>
    <course academic_year="2015" course_id="131566" class_number="11839" school_id="fas" section="001" term_code="fall">
        <catalog_info>
            <title short_title="IMMUN 378">T cell Biology and Cancer Immunology</title>
            <department code="MDSC">Medical Sciences</department>
            <course_group code="IMMUN">Immunology</course_group>
            <course_type>Thesis Research</course_type>
            <credits>4</credits>
        </catalog_info>
        <staff>
            <person id="d1e17604a1310" role="1" seniority_sort="1">
                <display_name>Kai Wucherpfennig</display_name>
            </person>
        </staff>
    </course>
</courses>